vision_counter/__init__.py
vision_counter/models/__init__.py
vision_counter/models/countr.py
vision_counter/utils/__init__.py
vision_counter/utils/hub.py
vision_counter-0.1.0.dist-info/LICENSE
vision_counter-0.1.0.dist-info/METADATA
vision_counter-0.1.0.dist-info/WHEEL
vision_counter-0.1.0.dist-info/top_level.txt
vision_counter-0.1.0.dist-info/RECORD
